credeo/__init__.py
credeo/main.py
credeo-0.0.1.dist-info/METADATA
credeo-0.0.1.dist-info/WHEEL
credeo-0.0.1.dist-info/entry_points.txt
credeo-0.0.1.dist-info/RECORD
