Metadata-Version: 2.1
Name: credeo
Version: 0.0.1
Summary: All popular Framework HF integration kit
Home-page: https://github.com/santhosh/
License: MIT
Author: Kammari Santhosh
Requires-Python: >=3.10,<4.0
Classifier: License :: OSI Approved :: MIT License
Classifier: Programming Language :: Python :: 3
Classifier: Programming Language :: Python :: 3.10
Classifier: Programming Language :: Python :: 3.11
Classifier: Programming Language :: Python :: 3.12
Classifier: Programming Language :: Python :: 3.13
Requires-Dist: ollama (>=0.4.5,<0.5.0)
Requires-Dist: openai (>=1.58.1,<2.0.0)
Project-URL: Repository, https://github.com/santhosh/
